server/__init__.py
server/server_.py
server/common/__init__.py
server/common/decos.py
server/common/descryptors.py
server/common/errors.py
server/common/metaclasses.py
server/common/utils.py
server/common/variables.py
server/doc/__init__.py
server/doc/source/__init__.py
server/doc/source/conf.py
server/forms_gui/__init__.py
server/forms_gui/add_user.py
server/forms_gui/config_window.py
server/forms_gui/remove_user.py
server/forms_gui/stat_window.py
server/logs/__init__.py
server/logs/server_log_config.py
server/test_unit/__init__.py
server_messenger_prog-0.1.dist-info/METADATA
server_messenger_prog-0.1.dist-info/WHEEL
server_messenger_prog-0.1.dist-info/top_level.txt
server_messenger_prog-0.1.dist-info/RECORD
