Metadata-Version: 2.1
Name: server-messenger-prog
Version: 0.1
Summary: Server packet
Author: Uegene Palymov
Author-email: palbimov@yandex.ru
License: UNKNOWN
Platform: UNKNOWN
Requires-Dist: PyQt5
Requires-Dist: sqlalchemy
Requires-Dist: pycryptodome
Requires-Dist: pycryptodomex
